pipdemo666/__init__.py
pipdemo666-0.2.dist-info/METADATA
pipdemo666-0.2.dist-info/WHEEL
pipdemo666-0.2.dist-info/top_level.txt
pipdemo666-0.2.dist-info/RECORD
