Metadata-Version: 2.1
Name: pipdemo666
Version: 0.2
Summary: clinical trial information retriver
Home-page: https://github.com/Bruce-chen-zt/pipdemo666
Author: bruce
Author-email: chenzetao2021@163.com
License: MIT
